azure/applicationinsights/__init__.py
azure/applicationinsights/application_insights_data_client.py
azure/applicationinsights/version.py
azure/applicationinsights/models/__init__.py
azure/applicationinsights/models/application_insights_data_client_enums.py
azure/applicationinsights/models/column.py
azure/applicationinsights/models/column_py3.py
azure/applicationinsights/models/error_detail.py
azure/applicationinsights/models/error_detail_py3.py
azure/applicationinsights/models/error_info.py
azure/applicationinsights/models/error_info_py3.py
azure/applicationinsights/models/error_response.py
azure/applicationinsights/models/error_response_py3.py
azure/applicationinsights/models/events_ai_info.py
azure/applicationinsights/models/events_ai_info_py3.py
azure/applicationinsights/models/events_application_info.py
azure/applicationinsights/models/events_application_info_py3.py
azure/applicationinsights/models/events_availability_result_info.py
azure/applicationinsights/models/events_availability_result_info_py3.py
azure/applicationinsights/models/events_availability_result_result.py
azure/applicationinsights/models/events_availability_result_result_py3.py
azure/applicationinsights/models/events_browser_timing_info.py
azure/applicationinsights/models/events_browser_timing_info_py3.py
azure/applicationinsights/models/events_browser_timing_result.py
azure/applicationinsights/models/events_browser_timing_result_py3.py
azure/applicationinsights/models/events_client_info.py
azure/applicationinsights/models/events_client_info_py3.py
azure/applicationinsights/models/events_client_performance_info.py
azure/applicationinsights/models/events_client_performance_info_py3.py
azure/applicationinsights/models/events_cloud_info.py
azure/applicationinsights/models/events_cloud_info_py3.py
azure/applicationinsights/models/events_custom_event_info.py
azure/applicationinsights/models/events_custom_event_info_py3.py
azure/applicationinsights/models/events_custom_event_result.py
azure_applicationinsights-0.1.1.dist-info/METADATA
azure_applicationinsights-0.1.1.dist-info/WHEEL
azure_applicationinsights-0.1.1.dist-info/top_level.txt
azure_applicationinsights-0.1.1.dist-info/RECORD
